package vm

/*
四种指令类型
*/
const (
	/*
		可以携带 3 个操作数，分别用 8、9、9 个比特表示，共计 39 条指令
	*/
	IABC = iota
	/*
		携带 A 和 Bx 两个操作数，分别占用 8 和 18 个比特，共计 3 条指令
	*/
	IABx
	/*
		携带 A 和 sBx 两个操作数，分别占用 8 和 18 个比特，共计 4 条指令
		**只有这种形式的指令中的 sBx 操作数会被解释成有符号整数**
	*/
	IAsBx
	/*
		携带一个操作数，占用 26 个比特，只有 1 条“指令”
		TODO：实际并不是真正的指令，只用来扩展其他指令操作数？
	*/
	IAx
)

/*
指令码
	所有指令均占用 32 个比特，其中低 6 比特用于操作码，高 26 比特用于操作数
	6 比特本身可表示 2^6=64 条指令，Lua 中共有 47 条指令，操作码从 0～46，详见下面的常量
*/
const (
	OP_MOVE = iota
	OP_LOADK
	OP_LOADKX
	OP_LOADBOOL
	OP_LOADNIL
	OP_GETUPVAL
	OP_GETTABUP
	OP_GETTABLE
	OP_SETTABUP
	OP_SETUPVAL
	OP_SETTABLE
	OP_NEWTABLE
	OP_SELF
	OP_ADD
	OP_SUB
	OP_MUL
	OP_MOD
	OP_POW
	OP_DIV
	OP_IDIV
	OP_BAND
	OP_BOR
	OP_BXOR
	OP_SHL
	OP_SHR
	OP_UNM
	OP_BNOT
	OP_NOT
	OP_LEN
	OP_CONCAT
	OP_JMP
	OP_EQ
	OP_LT
	OP_LE
	OP_TEST
	OP_TESTSET
	OP_CALL
	OP_TAILCALL
	OP_RETURN
	OP_FORLOOP
	OP_FORPREP
	OP_TFORCALL
	OP_TFORLOOP
	OP_SETLIST
	OP_CLOSURE
	OP_VARARG
	OP_EXTRAARG
)

/*
四种操作数类型
*/
const (
	/*
		操作数未被使用，如 MOVE 指令中的 C 操作数
	*/
	OpArgN = iota
	/*
		操作数已被使用，可能为布尔值、整数值、upvalue 索引、子函数索引等
	*/
	OpArgU
	/*
		操作数是寄存器（在 iABC 模式下）或一个跳转偏移（在 iAsBx 模式下）
	*/
	OpArgR
	/*
		操作数是常量或寄存器
			在 iABx 模式下表示常量表索引，比如 LOADK 指令
			在 iABC 模式下该操作数类型只能使用 9 个比特中的低 8 位，其中第 9 位为 1 表示常量表索引，否则为寄存器索引

		TODO：这样表示常量索引时应该只有 2^8=256 个值，但是实际测试时发现 Lua 对常量的数量似乎没有限制？
	*/
	OpArgK
)

/*
用于表示一条指令的基本信息，在 Lua 的实现中占用 1 个字节，这里为了方便转换成了结构体
*/
type opcode struct {
	// 表示当前指令是一个 test，下一条指令必须是一个跳转
	testFlag byte
	// 指令设置了寄存器 A
	setAFlag byte
	// B 操作数的类型
	argBMode byte
	// C 操作数的类型
	argCMode byte
	// 指令类型
	opMode byte
	// 操作码名称
	name string
}

/*
所有的 47 条指令以及其伪代码
*/
var opcodes = []opcode{
	/*     T  A    B       C     mode         name */
	opcode{0, 1, OpArgR, OpArgN, IABC /* */, "MOVE    "}, // R(A) := R(B)
	opcode{0, 1, OpArgK, OpArgN, IABx /* */, "LOADK   "}, // R(A) := Kst(Bx)
	opcode{0, 1, OpArgN, OpArgN, IABx /* */, "LOADKX  "}, // R(A) := Kst(extra arg)
	opcode{0, 1, OpArgU, OpArgU, IABC /* */, "LOADBOOL"}, // R(A) := (bool)B; if (C) pc++
	opcode{0, 1, OpArgU, OpArgN, IABC /* */, "LOADNIL "}, // R(A), R(A+1), ..., R(A+B) := nil
	opcode{0, 1, OpArgU, OpArgN, IABC /* */, "GETUPVAL"}, // R(A) := UpValue[B]
	opcode{0, 1, OpArgU, OpArgK, IABC /* */, "GETTABUP"}, // R(A) := UpValue[B][RK(C)]
	opcode{0, 1, OpArgR, OpArgK, IABC /* */, "GETTABLE"}, // R(A) := R(B)[RK(C)]
	opcode{0, 0, OpArgK, OpArgK, IABC /* */, "SETTABUP"}, // UpValue[A][RK(B)] := RK(C)
	opcode{0, 0, OpArgU, OpArgN, IABC /* */, "SETUPVAL"}, // UpValue[B] := R(A)
	opcode{0, 0, OpArgK, OpArgK, IABC /* */, "SETTABLE"}, // R(A)[RK(B)] := RK(C)
	opcode{0, 1, OpArgU, OpArgU, IABC /* */, "NEWTABLE"}, // R(A) := {} (size = B,C)
	opcode{0, 1, OpArgR, OpArgK, IABC /* */, "SELF    "}, // R(A+1) := R(B); R(A) := R(B)[RK(C)]
	opcode{0, 1, OpArgK, OpArgK, IABC /* */, "ADD     "}, // R(A) := RK(B) + RK(C)
	opcode{0, 1, OpArgK, OpArgK, IABC /* */, "SUB     "}, // R(A) := RK(B) - RK(C)
	opcode{0, 1, OpArgK, OpArgK, IABC /* */, "MUL     "}, // R(A) := RK(B) * RK(C)
	opcode{0, 1, OpArgK, OpArgK, IABC /* */, "MOD     "}, // R(A) := RK(B) % RK(C)
	opcode{0, 1, OpArgK, OpArgK, IABC /* */, "POW     "}, // R(A) := RK(B) ^ RK(C)
	opcode{0, 1, OpArgK, OpArgK, IABC /* */, "DIV     "}, // R(A) := RK(B) / RK(C)
	opcode{0, 1, OpArgK, OpArgK, IABC /* */, "IDIV    "}, // R(A) := RK(B) // RK(C)
	opcode{0, 1, OpArgK, OpArgK, IABC /* */, "BAND    "}, // R(A) := RK(B) & RK(C)
	opcode{0, 1, OpArgK, OpArgK, IABC /* */, "BOR     "}, // R(A) := RK(B) | RK(C)
	opcode{0, 1, OpArgK, OpArgK, IABC /* */, "BXOR    "}, // R(A) := RK(B) ~ RK(C)
	opcode{0, 1, OpArgK, OpArgK, IABC /* */, "SHL     "}, // R(A) := RK(B) << RK(C)
	opcode{0, 1, OpArgK, OpArgK, IABC /* */, "SHR     "}, // R(A) := RK(B) >> RK(C)
	opcode{0, 1, OpArgR, OpArgN, IABC /* */, "UNM     "}, // R(A) := -R(B)
	opcode{0, 1, OpArgR, OpArgN, IABC /* */, "BNOT    "}, // R(A) := ~R(B)
	opcode{0, 1, OpArgR, OpArgN, IABC /* */, "NOT     "}, // R(A) := not R(B)
	opcode{0, 1, OpArgR, OpArgN, IABC /* */, "LEN     "}, // R(A) := length of R(B)
	opcode{0, 1, OpArgR, OpArgR, IABC /* */, "CONCAT  "}, // R(A) := R(B).. ... ..R(C)
	opcode{0, 0, OpArgR, OpArgN, IAsBx /**/, "JMP     "}, // pc+=sBx; if (A) close all upvalues >= R(A - 1)
	opcode{1, 0, OpArgK, OpArgK, IABC /* */, "EQ      "}, // if ((RK(B) == RK(C)) ~= A) then pc++
	opcode{1, 0, OpArgK, OpArgK, IABC /* */, "LT      "}, // if ((RK(B) < RK(C)) ~= A) then pc++
	opcode{1, 0, OpArgK, OpArgK, IABC /* */, "LE      "}, // if ((RK(B) <= RK(C)) ~= A) then pc++
	opcode{1, 0, OpArgN, OpArgU, IABC /* */, "TEST    "}, // if not (R(A) <=> C) then pc++
	opcode{1, 1, OpArgR, OpArgU, IABC /* */, "TESTSET "}, // if (R(B) <=> C) then R(A) := R(B) else pc++
	opcode{0, 1, OpArgU, OpArgU, IABC /* */, "CALL    "}, // R(A), ... ,R(A+C-2) := R(A)(R(A+1), ... ,R(A+B-1))
	opcode{0, 1, OpArgU, OpArgU, IABC /* */, "TAILCALL"}, // return R(A)(R(A+1), ... ,R(A+B-1))
	opcode{0, 0, OpArgU, OpArgN, IABC /* */, "RETURN  "}, // return R(A), ... ,R(A+B-2)
	opcode{0, 1, OpArgR, OpArgN, IAsBx /**/, "FORLOOP "}, // R(A)+=R(A+2); if R(A) <?= R(A+1) then { pc+=sBx; R(A+3)=R(A) }
	opcode{0, 1, OpArgR, OpArgN, IAsBx /**/, "FORPREP "}, // R(A)-=R(A+2); pc+=sBx
	opcode{0, 0, OpArgN, OpArgU, IABC /* */, "TFORCALL"}, // R(A+3), ... ,R(A+2+C) := R(A)(R(A+1), R(A+2));
	opcode{0, 1, OpArgR, OpArgN, IAsBx /**/, "TFORLOOP"}, // if R(A+1) ~= nil then { R(A)=R(A+1); pc += sBx }
	opcode{0, 0, OpArgU, OpArgU, IABC /* */, "SETLIST "}, // R(A)[(C-1)*FPF+i] := R(A+i), 1 <= i <= B
	opcode{0, 1, OpArgU, OpArgN, IABx /* */, "CLOSURE "}, // R(A) := closure(KPROTO[Bx])
	opcode{0, 1, OpArgU, OpArgN, IABC /* */, "VARARG  "}, // R(A), R(A+1), ..., R(A+B-2) = vararg
	opcode{0, 0, OpArgU, OpArgU, IAx /* */, "EXTRAARG "}, // extra (larger) argument for previous opcode
}
